{
  "person_000": {
    "name": "aryan",
    "first_seen": "2025-11-23 02:00:38",
    "encounter_count": 112,
    "samples": 1,
    "last_updated": "2025-11-23 02:00:38",
    "last_seen": "2025-11-23 02:02:41"
  },
  "person_001": {
    "name": "aryan",
    "first_seen": "2026-03-14 04:14:42",
    "encounter_count": 193,
    "samples": 1,
    "last_updated": "2026-03-14 04:14:42",
    "last_seen": "2026-03-15 02:22:31"
  },
  "person_002": {
    "name": "aryan",
    "first_seen": "2026-03-15 02:18:32",
    "encounter_count": 477,
    "samples": 1,
    "last_updated": "2026-03-15 02:18:32",
    "last_seen": "2026-03-15 02:35:18"
  }
}